helloworld/__init__.py
helloworld/core.py
helloworld_test_fiap_package-1.0.0.dist-info/METADATA
helloworld_test_fiap_package-1.0.0.dist-info/WHEEL
helloworld_test_fiap_package-1.0.0.dist-info/top_level.txt
helloworld_test_fiap_package-1.0.0.dist-info/RECORD
